{
  "_fv": 79,
  "_type": "recipe",
  "definition": {
    "recipeType": "Crafting",
    "recipeRetstackSize": 9,
    "group": "",
    "unlockingItems": [],
    "cookingBookCategory": "MISC",
    "xpReward": 0.0,
    "cookingTime": 200,
    "craftingBookCategory": "MISC",
    "recipeShapeless": true,
    "recipeSlots": [
      {
        "value": "Blocks.GOLD_BLOCK"
      },
      {
        "value": "Blocks.GOLD_BLOCK"
      },
      {
        "value": "Blocks.GOLD_BLOCK"
      },
      {
        "value": "Blocks.GOLD_BLOCK"
      },
      {
        "value": "CUSTOM:Tomate"
      },
      {
        "value": "Blocks.GOLD_BLOCK"
      },
      {
        "value": "Blocks.GOLD_BLOCK"
      },
      {
        "value": "Blocks.GOLD_BLOCK"
      },
      {
        "value": "Blocks.GOLD_BLOCK"
      }
    ],
    "recipeReturnStack": {
      "value": "CUSTOM:Tomatedorado"
    },
    "name": "tomatedoradocraft",
    "namespace": "mod"
  }
}